my_lib_test_may_2019/__init__.py
my_lib_test_may_2019-0.0.1.dist-info/LICENSE
my_lib_test_may_2019-0.0.1.dist-info/WHEEL
my_lib_test_may_2019-0.0.1.dist-info/METADATA
my_lib_test_may_2019-0.0.1.dist-info/RECORD
