Metadata-Version: 2.1
Name: my_lib_test_may_2019
Version: 0.0.1
Summary: "
Home-page: https://github.com/Carreau/my_lib_test_may_2019
License: UNKNOWN
Author: Matthias Bussonnier
Author-email: mbussonnier@ucmerced.edu
Classifier: License :: OSI Approved :: MIT License
